{
    "kind": "domain",
    "domain": "0",
    "topics":
    {
        "5":
        {
            "kind": "topic",
            "metatraffic": false,
            "alias": "HelloWorld"
        }
    },
    "hosts":
    {
        "2":
        {
            "kind": "host",
            "metatraffic": false,
            "alias": "example_host_alias",
            "status": "OK",
            "users":
            {
                "3":
                {
                    "kind": "user",
                    "metatraffic": false,
                    "alias": "example_user_alias",
                    "status": "OK",
                    "processes":
                    {
                        "4":
                        {
                            "kind": "process",
                            "metatraffic": false,
                            "alias": "example_process1_alias",
                            "pid": "1234",
                            "status": "OK",
                            "participants":
                            {
                                "1":
                                {
                                    "kind": "participant",
                                    "metatraffic": false,
                                    "alias": "example_participant1_alias",
                                    "status": "OK",
                                    "app_id": "UNKNOWN_APP",
                                    "app_metadata": "",
                                    "endpoints":
                                    {
                                        "6":
                                        {
                                            "kind": "datawriter",
                                            "metatraffic": false,
                                            "alias": "example_publisher_alias",
                                            "status": "OK",
                                            "topic": "5"
                                        }
                                    }
                                }
                            }
                        },
                        "8":
                        {
                            "kind": "process",
                            "metatraffic": false,
                            "alias": "example_process2_alias",
                            "pid": "1235",
                            "status": "OK",
                            "participants":
                            {
                                "7":
                                {
                                    "kind": "participant",
                                    "metatraffic": false,
                                    "alias": "example_participant2_alias",
                                    "status": "OK",
                                    "app_id": "UNKNOWN_APP",
                                    "app_metadata": "",
                                    "endpoints":
                                    {
                                        "9":
                                        {
                                            "kind": "datareader",
                                            "metatraffic": false,
                                            "alias": "example_subscriber_alias",
                                            "status": "OK",
                                            "topic": "5"
                                        }
                                    }
                                }
                            }
                        }
                    }
                }
            }
        }
    }
}
